{
  "tasks": [
    {
      "id": 1,
      "title": "json-server",
      "detail": "typicode",
      "dueDate": "11/08/2021",
      "createdAt": "11/08/2021",
      "modifiedAt": null,
      "status": "TODO"
    },
    {
      "title": "test",
      "detail": "gggggggggg",
      "createdAt": "2021-11-08T06:48:07.756Z",
      "modifiedAt": "2021-11-08T11:53:46.449Z",
      "dueDate": "2021-11-23T06:48:15.274Z",
      "status": "TODO",
      "id": 2
    },
    {
      "title": "wertty",
      "detail": "yyyyyyyy",
      "dueDate": "2021-11-30T06:53:41.583Z",
      "createdAt": "2021-11-08T06:53:34.133Z",
      "status": "TODO",
      "modifiedAt": null,
      "id": 3
    }
  ]
}